ringcentral_engage_digital_source_sdk/__init__.py
ringcentral_engage_digital_source_sdk/app.py
ringcentral_engage_digital_source_sdk/config.py
ringcentral_engage_digital_source_sdk/rces.py
ringcentral_engage_digital_source_sdk/run_server.py
ringcentral_engage_digital_source_sdk/core/__init__.py
ringcentral_engage_digital_source_sdk/core/common.py
ringcentral_engage_digital_source_sdk/core/config_default.py
ringcentral_engage_digital_source_sdk/core/flask_request_parser.py
ringcentral_engage_digital_source_sdk/core/post_message.py
ringcentral_engage_digital_source_sdk/core/sign.py
ringcentral_engage_digital_source_sdk-0.0.1.dist-info/LICENSE
ringcentral_engage_digital_source_sdk-0.0.1.dist-info/METADATA
ringcentral_engage_digital_source_sdk-0.0.1.dist-info/WHEEL
ringcentral_engage_digital_source_sdk-0.0.1.dist-info/entry_points.txt
ringcentral_engage_digital_source_sdk-0.0.1.dist-info/top_level.txt
ringcentral_engage_digital_source_sdk-0.0.1.dist-info/RECORD
