Metadata-Version: 2.1
Name: ringcentral-engage-digital-source-sdk
Version: 0.0.1
Summary: RingCentral engage digital channel SDK Framework for Python
Home-page: https://github.com/ringcentral/engage-digital-source-sdk-python
Author: Drake Zhao @ RingCentral
Author-email: drake.zhao@ringcentral.com
License: UNKNOWN
Keywords: ringcentral,SDK,framework,Engage Digital
Platform: UNKNOWN
Classifier: Programming Language :: Python :: 3
Classifier: License :: OSI Approved :: MIT License
Classifier: Operating System :: OS Independent
Requires-Dist: pydash
Requires-Dist: flask
Requires-Dist: python-dotenv
